Metadata-Version: 1.0
Name: chaoyi-probability
Version: 0.1
Summary: Gaussian distributions
Home-page: UNKNOWN
Author: Chaoyi Wang
Author-email: UNKNOWN
License: UNKNOWN
Platform: UNKNOWN
